asb_tour/__init__.py
asb_tour/dlq_client.py
asb_tour/explorer.py
asb_tour/main.py
asb_tour/sub_client.py
asb_tour/topic_client.py
asb_tour/scripts/__init__.py
asb_tour/scripts/cli_script.py
asb_cli_explorer-0.1.8.dist-info/LICENSE
asb_cli_explorer-0.1.8.dist-info/METADATA
asb_cli_explorer-0.1.8.dist-info/WHEEL
asb_cli_explorer-0.1.8.dist-info/entry_points.txt
asb_cli_explorer-0.1.8.dist-info/top_level.txt
asb_cli_explorer-0.1.8.dist-info/RECORD
