Metadata-Version: 2.1
Name: asb-cli-explorer
Version: 0.1.8
Summary: Explore Azure service bus from command line
Home-page: https://github.com/cackharot/asb-cli-explorer
License: MIT
Keywords: service bus,servicebus,azure,azure service bus,messaging,amqp
Platform: Python3
Classifier: Programming Language :: Python
Classifier: Programming Language :: Python :: 3
Classifier: Intended Audience :: Developers
Classifier: Operating System :: OS Independent
Requires-Python: >=3.7.4
Requires-Dist: click
Requires-Dist: azure-servicebus
